README.md
setup.cfg
setup.py
regex4ocr/__init__.py
regex4ocr/main.py
regex4ocr.egg-info/PKG-INFO
regex4ocr.egg-info/SOURCES.txt
regex4ocr.egg-info/dependency_links.txt
regex4ocr.egg-info/not-zip-safe
regex4ocr.egg-info/requires.txt
regex4ocr.egg-info/top_level.txt
regex4ocr/logger/__init__.py
regex4ocr/logger/formatter.py
regex4ocr/parser/__init__.py
regex4ocr/parser/drm_scanner.py
regex4ocr/parser/extraction.py
regex4ocr/parser/parser.py
regex4ocr/parser/pre_process.py
regex4ocr/parser/type_casting.py
regex4ocr/parser/validation.py
regex4ocr/parser/yml_parser.py