Metadata-Version: 1.0
Name: regex4ocr
Version: 1.3.0
Summary: Extract data from OCR string results based on Document Regexp Models (DRMs).
Home-page: https://github.com/juntossomosmais/regex4ocr
Author: Igor Grillo Peternella
Author-email: igor.feq@gmail.com
License: MIT
Platform: UNKNOWN
